ParrotAnafiController/AnafiCamera.py
ParrotAnafiController/AnafiCameraControls.py
ParrotAnafiController/AnafiCameraMedia.py
ParrotAnafiController/AnafiController.py
ParrotAnafiController/AnafiPiloting.py
ParrotAnafiController/AnafiRTH.py
ParrotAnafiController/SoftwarePilot.py
ParrotAnafiController/__init__.py
ParrotAnafiController-1.0.1.dist-info/METADATA
ParrotAnafiController-1.0.1.dist-info/WHEEL
ParrotAnafiController-1.0.1.dist-info/top_level.txt
ParrotAnafiController-1.0.1.dist-info/RECORD
