Metadata-Version: 2.1
Name: ParrotAnafiController
Version: 1.0.1
Summary: Wrapper for Parrot Olympe
Home-page: https://github.com/boredbot2/Parrot-Controller
Author: Kevyn Angueira Irizarry
Author-email: kevyn.angueira@gmail.com
License: UNKNOWN
Platform: UNKNOWN
Requires-Python: >=3.6
Requires-Dist: cv2 (>=2.0.2)
Requires-Dist: requests (>=2.27.1)
Requires-Dist: olympe (>=0.0.1)
